livescore/Livescore2017.py
livescore/Livescore2018.py
livescore/Livescore2019.py
livescore/LivescoreBase.py
livescore/__init__.py
livescore/details.py
livescore/simpleocr_utils/__init__.py
livescore/simpleocr_utils/feature_extraction.py
livescore/simpleocr_utils/numpy_utils.py
livescore/simpleocr_utils/opencv_utils.py
livescore/simpleocr_utils/processor.py
livescore/simpleocr_utils/segmentation.py
livescore/simpleocr_utils/segmentation_aux.py
livescore/simpleocr_utils/segmentation_filters.py
livescore/templates/2018_boost.png
livescore/templates/2018_force.png
livescore/templates/2018_levitate.png
livescore/templates/score_overlay_2017.png
livescore/templates/score_overlay_2018.png
livescore/templates/score_overlay_2019.png
livescore/tessdata/digits.traineddata
livescore/tessdata/eng.traineddata
livescore/training_data/digits.pkl
livescore-2019.0.0.dist-info/LICENSE
livescore-2019.0.0.dist-info/METADATA
livescore-2019.0.0.dist-info/WHEEL
livescore-2019.0.0.dist-info/top_level.txt
livescore-2019.0.0.dist-info/RECORD
