Metadata-Version: 2.1
Name: livescore
Version: 2019.0.0
Summary: Get FRC scores from an image
Home-page: https://github.com/andrewda/frc-livescore
Author: Andrew Dassonville
Author-email: dassonville.andrew@gmail.com
License: MIT
Keywords: frc,score,robotics
Platform: UNKNOWN
